{
    "19": [
        {
            "result": "Battle Lost",
            "team1": {
                "player": "initiate_726597",
                "team": [
                    "Wizard of Eastwood",
                    "Unicorn Mustang",
                    "Mycelic Morphoid",
                    "Khmer Princess",
                    "Regal Peryton"
                ]
            },
            "team2": {
                "player": "voi175",
                "team": [
                    "Obsidian",
                    "Unicorn Mustang",
                    "Khmer Princess",
                    "Regal Peryton"
                ]
            }
        }
    ],
    "22": [
        {
            "result": "Battle Lost",
            "team1": {
                "player": "initiate_726597",
                "team": [
                    "Tarsa",
                    "Living Lava",
                    "Serpentine Spy",
                    "Lava Spider",
                    "Tenyii Striker"
                ]
            },
            "team2": {
                "player": "kiki88",
                "team": [
                    "Kelya Frendul",
                    "Serpent of Eld",
                    "Kulu Swimhunter",
                    "Albatross",
                    "Ice Pixie",
                    "Tower Griffin"
                ]
            }
        }
    ],
    "99": [
        {
            "result": "Battle Won",
            "team1": {
                "player": "initiate_726597",
                "team": [
                    "Obsidian",
                    "Venari Knifer",
                    "Unicorn Mustang",
                    "Regal Peryton",
                    "Mycelic Slipspawn",
                    "Khmer Princess",
                    "Goblin Psychic"
                ]
            },
            "team2": {
                "player": "dth02",
                "team": [
                    "Kelya Frendul",
                    "Serpent of Eld",
                    "Flying Squid",
                    "Disintegrator",
                    "Supply Runner",
                    "Deeplurker",
                    "Mantoid"
                ]
            }
        }
    ],
    "28": [
        {
            "result": "Battle Lost",
            "team1": {
                "player": "err45",
                "team": [
                    "Tarsa",
                    "Radiated Scorcher",
                    "Living Lava",
                    "Radiated Brute",
                    "Serpentine Spy",
                    "Tenyii Striker",
                    "Lava Spider"
                ]
            },
            "team2": {
                "player": "initiate_975111",
                "team": [
                    "Kelya Frendul",
                    "Serpent of Eld",
                    "Deeplurker",
                    "Merdaali Guardian",
                    "Scavo Hireling",
                    "Feasting Seaweed",
                    "Albatross"
                ]
            }
        }
    ],
    "26": [
        {
            "result": "Battle Lost",
            "team1": {
                "player": "initiate_975111",
                "team": [
                    "Thaddius Brood",
                    "Cursed Windeku",
                    "Riftwing",
                    "Death Elemental",
                    "Undead Badger",
                    "Xenith Archer"
                ]
            },
            "team2": {
                "player": "tuehung9",
                "team": [
                    "Obsidian",
                    "Unicorn Mustang",
                    "Mycelic Morphoid",
                    "Goblin Psychic",
                    "Khmer Princess",
                    "Regal Peryton"
                ]
            }
        }
    ],
    "20": [
        {
            "result": "Battle Lost",
            "team1": {
                "player": "initiate_975111",
                "team": [
                    "Thaddius Brood",
                    "Cursed Windeku",
                    "Cursed Slimeball",
                    "Death Elemental",
                    "Undead Badger",
                    "Life Sapper",
                    "Carrion Shade"
                ]
            },
            "team2": {
                "player": "initiate736552",
                "team": [
                    "Thaddius Brood",
                    "Cursed Windeku",
                    "Undead Badger",
                    "Silent Sha-vi",
                    "Death Elemental"
                ]
            }
        }
    ],
    "22": [
        {
            "result": "Battle Lost",
            "team1": {
                "player": "initiate_975111",
                "team": [
                    "Tarsa",
                    "Living Lava",
                    "Serpentine Spy",
                    "Lava Spider",
                    "Tenyii Striker"
                ]
            },
            "team2": {
                "player": "fdzwl47854636",
                "team": [
                    "Tarsa",
                    "Radiated Scorcher",
                    "Living Lava",
                    "Serpentine Spy",
                    "Tenyii Striker",
                    "Scavo Chemist"
                ]
            }
        }
    ]
}